{"fomc_doc": {"meeting_date": "1999-06-30", "paragraphs": ["\r\n\tLabor markets have continued to tighten over recent quarters, but strengthening productivity growth has contained inflationary pressures.\r\n", "\r\n\tOwing to the uncertain resolution of the balance of conflicting forces in the economy going forward, the FOMC has chosen to adopt a directive that includes no predilection about near-term policy action.  The Committee, nonetheless, recognizes that in the current dynamic environment it must be especially alert to the emergence, or potential emergence, of inflationary forces that could undermine economic growth.\r\n\r\n\r\n", "\n1999 Monetary policy\n"], "doc_type": "St"}, "entity_sentiments": {"quarters": {"score": -0.10000000149011612, "magnitude": 0.10000000149011612, "salience": 0.18408724665641785}, "forces": {"score": -0.10000000149011612, "magnitude": 0.10000000149011612, "salience": 0.027396995574235916}}, "paragraph_count": 3, "word_count": 81, "n_gram_count": {"1": 81, "2": 80, "3": 79}, "pos_tags_count": {"noun_count": 15, "verb_count": 4, "adjective_count": 11}, "change_in_vix": null, "change_in_s_n_p_500": null}